kiwitcms_tap_plugin-12.8.1.data/scripts/tcms-tap-plugin
tcms_tap_plugin/__init__.py
tcms_tap_plugin/version.py
kiwitcms_tap_plugin-12.8.1.dist-info/LICENSE
kiwitcms_tap_plugin-12.8.1.dist-info/METADATA
kiwitcms_tap_plugin-12.8.1.dist-info/WHEEL
kiwitcms_tap_plugin-12.8.1.dist-info/top_level.txt
kiwitcms_tap_plugin-12.8.1.dist-info/RECORD
