Metadata-Version: 2.1
Name: kiwitcms-tap-plugin
Version: 12.8.1
Summary: Test Anything Protocol (TAP) plugin for Kiwi TCMS test case management system
Home-page: https://github.com/kiwitcms/tap-plugin
Author: Kiwi TCMS
Author-email: info@kiwitcms.org
License: GPLv3+
Classifier: Development Status :: 4 - Beta
Classifier: Environment :: Console
Classifier: Intended Audience :: Developers
Classifier: Intended Audience :: System Administrators
Classifier: License :: OSI Approved :: GNU General Public License v3 or later (GPLv3+)
Classifier: Operating System :: POSIX
Classifier: Programming Language :: Python
Classifier: Programming Language :: Python :: 3.8
Classifier: Programming Language :: Python :: 3.11
Classifier: Topic :: Software Development
Classifier: Topic :: Software Development :: Libraries :: Python Modules
Classifier: Topic :: Software Development :: Quality Assurance
Classifier: Topic :: Software Development :: Testing
License-File: LICENSE
Requires-Dist: tap.py (==3.1)
Requires-Dist: tcms-api (>=12.8.1)
